spplot/__init__.py
spplot/__main__.py
spplot/menu.py
spplot/meta.py
spplot/spplot.py
spplot-0.0.2.dist-info/METADATA
spplot-0.0.2.dist-info/WHEEL
spplot-0.0.2.dist-info/entry_points.txt
spplot-0.0.2.dist-info/top_level.txt
spplot-0.0.2.dist-info/RECORD
