Metadata-Version: 2.1
Name: spplot
Version: 0.0.2
Summary: command-line serial plotter
Home-page: https://github.com/adzierzanowski/spplot
Author: Aleksander Dzierżanowski
Author-email: a.dzierzanowski1@gmail.com
License: MIT
Platform: UNKNOWN
Classifier: Development Status :: 3 - Alpha
Classifier: Environment :: Console
Classifier: Intended Audience :: Developers
Classifier: Intended Audience :: End Users/Desktop
Classifier: Intended Audience :: Information Technology
Classifier: Intended Audience :: Science/Research
Classifier: License :: OSI Approved :: MIT License
Classifier: Operating System :: POSIX
Classifier: Operating System :: Unix
Classifier: Programming Language :: Python :: 3.6
Classifier: Topic :: Scientific/Engineering :: Information Analysis
Classifier: Topic :: Scientific/Engineering :: Visualization
Classifier: Topic :: Software Development :: Embedded Systems
Classifier: Topic :: Terminals :: Serial
Classifier: Topic :: Utilities
Requires-Python: >=3.6
Requires-Dist: drawille
Requires-Dist: pyserial
